MANIFEST.in
README.rst
bottle_redis.py
requirements.txt
setup.py
bottle_redis.egg-info/PKG-INFO
bottle_redis.egg-info/SOURCES.txt
bottle_redis.egg-info/dependency_links.txt
bottle_redis.egg-info/requires.txt
bottle_redis.egg-info/top_level.txt