Metadata-Version: 1.1
Name: bottle-redis
Version: 0.2.3
Summary: Redis integration for Bottle.
Home-page: https://github.com/bottlepy/bottle-redis
Author: Sean M. Collins
Author-email: sean@coreitpro.com
License: MIT
Platform: any
Classifier: Environment :: Web Environment
Classifier: Intended Audience :: Developers
Classifier: License :: OSI Approved :: MIT License
Classifier: Operating System :: OS Independent
Classifier: Programming Language :: Python
Classifier: Topic :: Internet :: WWW/HTTP :: Dynamic Content
Classifier: Topic :: Software Development :: Libraries :: Python Modules
Classifier: Framework :: Bottle
